pydantic/__init__.cpython-38-x86_64-linux-gnu.so
pydantic/__init__.py
pydantic/_hypothesis_plugin.cpython-38-x86_64-linux-gnu.so
pydantic/_hypothesis_plugin.py
pydantic/annotated_types.cpython-38-x86_64-linux-gnu.so
pydantic/annotated_types.py
pydantic/class_validators.cpython-38-x86_64-linux-gnu.so
pydantic/class_validators.py
pydantic/color.cpython-38-x86_64-linux-gnu.so
pydantic/color.py
pydantic/config.cpython-38-x86_64-linux-gnu.so
pydantic/config.py
pydantic/dataclasses.cpython-38-x86_64-linux-gnu.so
pydantic/dataclasses.py
pydantic/datetime_parse.cpython-38-x86_64-linux-gnu.so
pydantic/datetime_parse.py
pydantic/decorator.cpython-38-x86_64-linux-gnu.so
pydantic/decorator.py
pydantic/env_settings.cpython-38-x86_64-linux-gnu.so
pydantic/env_settings.py
pydantic/error_wrappers.cpython-38-x86_64-linux-gnu.so
pydantic/error_wrappers.py
pydantic/errors.cpython-38-x86_64-linux-gnu.so
pydantic/errors.py
pydantic/fields.cpython-38-x86_64-linux-gnu.so
pydantic/fields.py
pydantic/generics.py
pydantic/json.cpython-38-x86_64-linux-gnu.so
pydantic/json.py
pydantic/main.cpython-38-x86_64-linux-gnu.so
pydantic/main.py
pydantic/mypy.cpython-38-x86_64-linux-gnu.so
pydantic/mypy.py
pydantic/networks.cpython-38-x86_64-linux-gnu.so
pydantic/networks.py
pydantic/parse.cpython-38-x86_64-linux-gnu.so
pydantic/parse.py
pydantic/py.typed
pydantic/schema.cpython-38-x86_64-linux-gnu.so
pydantic/schema.py
pydantic/tools.cpython-38-x86_64-linux-gnu.so
pydantic/tools.py
pydantic/types.cpython-38-x86_64-linux-gnu.so
pydantic/types.py
pydantic/typing.cpython-38-x86_64-linux-gnu.so
pydantic/typing.py
pydantic/utils.cpython-38-x86_64-linux-gnu.so
pydantic/utils.py
pydantic/validators.cpython-38-x86_64-linux-gnu.so
pydantic/validators.py
pydantic/version.cpython-38-x86_64-linux-gnu.so
pydantic/version.py
pydantic/v1/__init__.py
pydantic/v1/_hypothesis_plugin.py
pydantic/v1/annotated_types.py
pydantic/v1/class_validators.py
pydantic-1.10.26.dist-info/LICENSE
pydantic-1.10.26.dist-info/METADATA
pydantic-1.10.26.dist-info/WHEEL
pydantic-1.10.26.dist-info/entry_points.txt
pydantic-1.10.26.dist-info/top_level.txt
pydantic-1.10.26.dist-info/RECORD
